.gitignore
.readthedocs.yml
CONTRIBUTING.md
LICENSE
MANIFEST.in
README.rst
pyproject.toml
setup.py
tox.ini
.github/workflows/ci.yml
aesop/__init__.py
aesop/activity.py
aesop/catalog.py
aesop/conftest.py
aesop/cython_version.py
aesop/masking.py
aesop/phoenix.py
aesop/setup_package.py
aesop/spectra.py
aesop/spectral_type.py
aesop/utils.py
aesop/version.py
aesop/tests/__init__.py
aesop/tests/test_spectrum1d.py
aesop_arces.egg-info/PKG-INFO
aesop_arces.egg-info/SOURCES.txt
aesop_arces.egg-info/dependency_links.txt
aesop_arces.egg-info/not-zip-safe
aesop_arces.egg-info/requires.txt
aesop_arces.egg-info/top_level.txt
docs/.rtd_environment.yaml
docs/Makefile
docs/api.rst
docs/conf.py
docs/getting_started.rst
docs/index.rst
docs/install.rst
docs/iraf.rst
docs/paper.bib
docs/paper.md
docs/references.txt
docs/_templates/autosummary/base.rst
docs/_templates/autosummary/class.rst
docs/_templates/autosummary/module.rst
iraf/ReduceARCES.cl
iraf/database/apechtrace130522
iraf/database/badpix.txt
iraf/database/ecarcnewref.ec
notebooks/example.ipynb