Metadata-Version: 2.4
Name: aesop-arces
Version: 0.5
Summary: Exposure time calculator for APO/ARCES
Author: Trevor Dorn-Wallenstein
Author-email: Brett Morris <morrisbrettm@gmail.com>
License: MIT License
Project-URL: repository, https://github.com/bmorris3/aesop
Requires-Python: >=3.9
License-File: LICENSE
Requires-Dist: astropy
Requires-Dist: numpy
Requires-Dist: matplotlib
Requires-Dist: h5py
Requires-Dist: pytest-astropy
Requires-Dist: specutils
Requires-Dist: scipy
Requires-Dist: astroquery
Provides-Extra: test
Requires-Dist: pytest-doctestplus; extra == "test"
Requires-Dist: pytest>=4.6.0; extra == "test"
Requires-Dist: pytest-astropy; extra == "test"
Provides-Extra: docs
Requires-Dist: sphinx; extra == "docs"
Requires-Dist: sphinx-automodapi; extra == "docs"
Requires-Dist: tomli; python_version < "3.11" and extra == "docs"
Requires-Dist: sphinx-astropy[confv2]; extra == "docs"
Requires-Dist: sphinx-rtd-theme; extra == "docs"
Requires-Dist: matplotlib; extra == "docs"
Dynamic: license-file
